hue_modules/__init__.py
hue_modules/color/__init__.py
hue_modules/color/main.py
hue_modules/list/__init__.py
hue_modules/list/main.py
hue_modules/switch/__init__.py
hue_modules/switch/main.py
hue_modules/util/__init__.py
hue_modules/util/bridge.py
huecli-2.0.1.data/scripts/hue
huecli-2.0.1.dist-info/METADATA
huecli-2.0.1.dist-info/WHEEL
huecli-2.0.1.dist-info/top_level.txt
huecli-2.0.1.dist-info/RECORD
