Metadata-Version: 2.1
Name: huecli
Version: 2.0.1
Summary: A simple cli app for controlling hue lights
Home-page: https://github.com/gageleblanc/hue
Author: Gage LeBlanc
Author-email: gleblanc@symnet.io
License: UNKNOWN
Platform: UNKNOWN
Classifier: Programming Language :: Python :: 3
Classifier: License :: OSI Approved :: GNU General Public License v3 (GPLv3)
Classifier: Operating System :: OS Independent
Requires-Dist: clilib (>=1.8.0)
Requires-Dist: phue
